pysparkmlclustering/__init__.py
pysparkmlclustering/hola.py
pysparkmlclustering-2.0.dist-info/METADATA
pysparkmlclustering-2.0.dist-info/WHEEL
pysparkmlclustering-2.0.dist-info/top_level.txt
pysparkmlclustering-2.0.dist-info/RECORD
