Metadata-Version: 2.4
Name: pysparkmlclustering
Version: 2.0
Author: Nick Fury
Author-email: nmercado506@gmail.com
Classifier: Programming Language :: Python :: 3
Classifier: License :: OSI Approved :: MIT License
Requires-Python: >=3.6
Requires-Dist: pyperclip
Dynamic: author
Dynamic: author-email
Dynamic: classifier
Dynamic: requires-dist
Dynamic: requires-python
